README
setup.py
src/sslstrip/ClientRequest.py
src/sslstrip/CookieCleaner.py
src/sslstrip/DnsCache.py
src/sslstrip/SSLServerConnection.py
src/sslstrip/ServerConnection.py
src/sslstrip/ServerConnectionFactory.py
src/sslstrip/StrippingProxy.py
src/sslstrip/URLMonitor.py
src/sslstrip/__init__.py
src/sslstrip/sslstrip.py
src/sslstrip.egg-info/PKG-INFO
src/sslstrip.egg-info/SOURCES.txt
src/sslstrip.egg-info/dependency_links.txt
src/sslstrip.egg-info/entry_points.txt
src/sslstrip.egg-info/requires.txt
src/sslstrip.egg-info/top_level.txt