Metadata-Version: 1.0
Name: sslstrip
Version: 0.9.2
Summary: A MITM tool that implements Moxie Marlinspike's HTTPS stripping attacks.
Home-page: https://github.com/graingert/sslstrip/
Author: Moxie Marlinspike
Author-email: moxie@thoughtcrime.org
License: GPL
Platform: UNKNOWN
